.gitignore
README.md
VERSION
requirements.txt
setup.py
raspi_node/__init__.py
raspi_node/__main__.py
raspi_node/config.py
raspi_node/db.py
raspi_node/gui.py
raspi_node/models.py
raspi_node/util.py
raspi_node/web.py
raspi_node.egg-info/PKG-INFO
raspi_node.egg-info/SOURCES.txt
raspi_node.egg-info/dependency_links.txt
raspi_node.egg-info/requires.txt
raspi_node.egg-info/top_level.txt
raspi_node/api/__init__.py
raspi_node/api/cli.py
raspi_node/api/collection.py