Metadata-Version: 1.0
Name: raspi-node
Version: 0.2.1
Summary: Raspberry Pi based LoRaWAN sensor node base station
Home-page: UNKNOWN
Author: Mirko Mälicke
Author-email: mirko@hydrocode.de
License: UNKNOWN
Platform: UNKNOWN
